[
  {
    "listingId": "2449543",
    "url": "https://www.bizbuysell.com/business-opportunity/dayton-4-territory-mosquito-shield-franchise-owner-financing/2449543/",
    "title": "Dayton 4 Territory Mosquito Shield Franchise - Owner Financing!",
    "location": "Dayton, OH",
    "askingPrice": null,
    "cashFlow": null,
    "descriptionSnippet": "Dayton, OH",
    "sourceUrl": "https://www.bizbuysell.com/ohio/pest-control-businesses-for-sale/"
  },
  {
    "listingId": "2361471",
    "url": "https://www.bizbuysell.com/business-opportunity/rid-the-neighborhood-of-pests-with-24-cash-flow-margin/2361471/",
    "title": "Rid the Neighborhood of Pests with 24% Cash Flow Margin",
    "location": "Clermont County, OH",
    "askingPrice": null,
    "cashFlow": 328814,
    "descriptionSnippet": "Clermont County, OH",
    "sourceUrl": "https://www.bizbuysell.com/ohio/pest-control-businesses-for-sale/"
  }
]